kif_lib/__init__.py
kif_lib/__version__.py
kif_lib/cache.py
kif_lib/cli.py
kif_lib/error.py
kif_lib/functools.py
kif_lib/itertools.py
kif_lib/py.typed
kif_lib/rdflib.py
kif_lib/typing.py
kif_lib/codec/__init__.py
kif_lib/codec/dot.py
kif_lib/codec/markdown.py
kif_lib/codec/options.py
kif_lib/codec/rdf/__init__.py
kif_lib/codec/rdf/encoder.py
kif_lib/codec/rdf/options.py
kif_lib/codec/sparql/__init__.py
kif_lib/codec/sparql/decoder.py
kif_lib/compiler/__init__.py
kif_lib/compiler/compiler.py
kif_lib/compiler/options.py
kif_lib/compiler/sparql/__init__.py
kif_lib/compiler/sparql/builder.py
kif_lib/compiler/sparql/compiler.py
kif_lib/compiler/sparql/filter_compiler.py
kif_lib/compiler/sparql/options.py
kif_lib/compiler/sparql/results.py
kif_lib/compiler/sparql/substitution.py
kif_lib/compiler/sparql/mapping/__init__.py
kif_lib/compiler/sparql/mapping/dbpedia.py
kif_lib/compiler/sparql/mapping/dbpedia_options.py
kif_lib/compiler/sparql/mapping/mapping.py
kif_lib/compiler/sparql/mapping/options.py
kif_lib/compiler/sparql/mapping/pubchem.py
kif_lib/compiler/sparql/mapping/pubchem_options.py
kif_lib/compiler/sparql/mapping/wikidata.py
kif_lib/compiler/sparql/mapping/wikidata_options.py
kif_lib/context/__init__.py
kif_lib/context/context.py
kif_lib/context/options.py
kif_lib/context/registry.py
kif_lib/context/section.py
kif_lib/engine/__init__.py
kif_lib/engine/abc.py
kif_lib/engine/options.py
kif_lib/model/__init__.py
kif_lib/model/constraint.py
kif_lib/model/filter.py
kif_lib/model/fingerprint.py
kif_lib/model/flags.py
kif_lib/model/graph.py
kif_lib/model/kif_object.py
kif_lib/model/object.py
kif_lib/model/options.py
kif_lib/model/path.py
kif_lib/model/pattern.py
kif_lib/model/rank.py
kif_lib/model/statement.py
kif_lib/model/pair/__init__.py
kif_lib/model/pair/closed_term_pair.py
kif_lib/model/pair/value_pair.py
kif_lib/model/set/__init__.py
kif_lib/model/set/closed_term_set.py
kif_lib/model/set/reference_record_set.py
kif_lib/model/set/snak_set.py
kif_lib-0.12.0.dist-info/licenses/LICENSE
kif_lib-0.12.0.dist-info/METADATA
kif_lib-0.12.0.dist-info/WHEEL
kif_lib-0.12.0.dist-info/entry_points.txt
kif_lib-0.12.0.dist-info/top_level.txt
kif_lib-0.12.0.dist-info/RECORD
