Metadata-Version: 2.4
Name: kif-lib
Version: 0.12.0
Summary: A knowledge integration framework based on Wikidata
Home-page: https://github.com/IBM/kif
Author: IBM
Author-email: Guilherme.Lima@ibm.com
License: Apache-2.0
Classifier: License :: OSI Approved :: Apache Software License
Classifier: Programming Language :: Python
Classifier: Programming Language :: Python :: 3
Classifier: Programming Language :: Python :: 3.9
Classifier: Programming Language :: Python :: 3.10
Classifier: Programming Language :: Python :: 3.11
Classifier: Programming Language :: Python :: 3.12
Classifier: Programming Language :: Python :: 3.13
Requires-Python: >=3.9
License-File: LICENSE
Requires-Dist: httpx
Requires-Dist: lark
Requires-Dist: more_itertools
Requires-Dist: networkx
Requires-Dist: rdflib
Requires-Dist: types-networkx
Requires-Dist: typing-extensions
Provides-Extra: all
Requires-Dist: myst_nb; extra == "all"
Requires-Dist: sphinx-rtd-theme; extra == "all"
Requires-Dist: click; extra == "all"
Requires-Dist: ddgs; extra == "all"
Requires-Dist: graphviz; extra == "all"
Requires-Dist: jpype1; extra == "all"
Requires-Dist: pandas; extra == "all"
Requires-Dist: pandas-stubs; extra == "all"
Requires-Dist: rich; extra == "all"
Requires-Dist: types-click; extra == "all"
Requires-Dist: flake8; extra == "all"
Requires-Dist: isort; extra == "all"
Requires-Dist: mypy; extra == "all"
Requires-Dist: pylint; extra == "all"
Requires-Dist: pyright; extra == "all"
Requires-Dist: pytest; extra == "all"
Requires-Dist: pytest-asyncio; extra == "all"
Requires-Dist: pytest-cov; extra == "all"
Requires-Dist: pytest-mypy; extra == "all"
Requires-Dist: pyupgrade; extra == "all"
Requires-Dist: setuptools; extra == "all"
Requires-Dist: tox; extra == "all"
Provides-Extra: docs
Requires-Dist: myst_nb; extra == "docs"
Requires-Dist: sphinx-rtd-theme; extra == "docs"
Provides-Extra: extra
Requires-Dist: click; extra == "extra"
Requires-Dist: ddgs; extra == "extra"
Requires-Dist: graphviz; extra == "extra"
Requires-Dist: jpype1; extra == "extra"
Requires-Dist: pandas; extra == "extra"
Requires-Dist: pandas-stubs; extra == "extra"
Requires-Dist: rich; extra == "extra"
Requires-Dist: types-click; extra == "extra"
Provides-Extra: tests
Requires-Dist: flake8; extra == "tests"
Requires-Dist: isort; extra == "tests"
Requires-Dist: mypy; extra == "tests"
Requires-Dist: pylint; extra == "tests"
Requires-Dist: pyright; extra == "tests"
Requires-Dist: pytest; extra == "tests"
Requires-Dist: pytest-asyncio; extra == "tests"
Requires-Dist: pytest-cov; extra == "tests"
Requires-Dist: pytest-mypy; extra == "tests"
Requires-Dist: pyupgrade; extra == "tests"
Requires-Dist: setuptools; extra == "tests"
Requires-Dist: tox; extra == "tests"
Dynamic: author
Dynamic: author-email
Dynamic: classifier
Dynamic: description
Dynamic: description-content-type
Dynamic: home-page
Dynamic: license
Dynamic: license-file
Dynamic: provides-extra
Dynamic: requires-dist
Dynamic: requires-python
Dynamic: summary
